finicky/__init__.py
finicky/schema.py
finicky/validators.py
Finicky-0.0.3.dist-info/LICENSE
Finicky-0.0.3.dist-info/METADATA
Finicky-0.0.3.dist-info/WHEEL
Finicky-0.0.3.dist-info/entry_points.txt
Finicky-0.0.3.dist-info/top_level.txt
Finicky-0.0.3.dist-info/RECORD
