Metadata-Version: 2.1
Name: Finicky
Version: 0.0.3
Summary: Easy Data Validation
Home-page: https://github.com/yaaminu/finicky
Author: Aminu Abdul Manaf
Author-email: afolanyaaminu@gmai.com
License: MIT
Platform: UNKNOWN
Classifier: License :: OSI Approved :: MIT License
Classifier: Programming Language :: Python :: 3
Classifier: Programming Language :: Python :: 3.7
Requires-Python: >=3.6
